server/__init__.py
server/__main__.py
server/server.py
browser_use_mcp_server/__init__.py
browser_use_mcp_server/cli.py
browser_use_mcp_server/server.py
qwen_browser_use_mcp_server-0.1.0.dist-info/METADATA
qwen_browser_use_mcp_server-0.1.0.dist-info/WHEEL
qwen_browser_use_mcp_server-0.1.0.dist-info/entry_points.txt
qwen_browser_use_mcp_server-0.1.0.dist-info/licenses/LICENSE
qwen_browser_use_mcp_server-0.1.0.dist-info/RECORD
