Metadata-Version: 2.4
Name: qwen-browser-use-mcp-server
Version: 0.1.0
Summary: MCP browser-use server library
License: MIT
License-File: LICENSE
Classifier: Operating System :: OS Independent
Classifier: Programming Language :: Python :: 3
Requires-Python: <4.0,>=3.11
Requires-Dist: anyio
Requires-Dist: asyncio>=3.4.3
Requires-Dist: browser-use>=0.1.40
Requires-Dist: click>=8.1.8
Requires-Dist: httpx>=0.28.1
Requires-Dist: langchain-openai>=0.3.1
Requires-Dist: mcp>=1.3.0
Requires-Dist: playwright>=1.50.0
Requires-Dist: pydantic>=2.10.6
Requires-Dist: python-dotenv
Requires-Dist: python-json-logger>=2.0.7
Requires-Dist: starlette
Requires-Dist: uvicorn
Provides-Extra: dev
Requires-Dist: black>=23.0.0; extra == 'dev'
Requires-Dist: browser-use-mcp-server[test]; extra == 'dev'
Requires-Dist: isort>=5.12.0; extra == 'dev'
Requires-Dist: mypy>=1.0.0; extra == 'dev'
Requires-Dist: ruff>=0.5.5; extra == 'dev'
Provides-Extra: test
Requires-Dist: pytest-asyncio>=0.21.0; extra == 'test'
Requires-Dist: pytest-cov>=4.1.0; extra == 'test'
Requires-Dist: pytest>=7.0.0; extra == 'test'
